Authentication/__init__.py
robotframework_Authentication-1.0.5.dist-info/METADATA
robotframework_Authentication-1.0.5.dist-info/WHEEL
robotframework_Authentication-1.0.5.dist-info/top_level.txt
robotframework_Authentication-1.0.5.dist-info/RECORD
