Metadata-Version: 2.1
Name: robotframework-Authentication
Version: 1.0.5
Summary: Permet de se connecter à un portail.
Home-page: 
Author: ADSN GROUP
Author-email: 
License: MIT
Platform: UNKNOWN
Classifier: License :: OSI Approved :: MIT License
Classifier: Programming Language :: Python :: 3
Classifier: Programming Language :: Python :: 3.6
Classifier: Programming Language :: Python :: 3.7
Classifier: Programming Language :: Python :: 3.8
